certpy/__init__.py
certpy/__main__.py
certpy/utils.py
certpy-0.1.1.dist-info/entry_points.txt
certpy-0.1.1.dist-info/WHEEL
certpy-0.1.1.dist-info/METADATA
certpy-0.1.1.dist-info/licenses/LICENSE
certpy-0.1.1.dist-info/RECORD
