Metadata-Version: 2.1
Name: certpy
Version: 0.1.1
Summary: Self-signed SSL certificate generator
License: MIT
Author-email: aprilahijriyan <hijriyan23@gmail.com>
Requires-Python: >=3.7
Requires-Dist: PyYAML>=6.0
Requires-Dist: pyOpenSSL>=22.1.0
Requires-Dist: rich>=10.11.0
Requires-Dist: typer>=0.6.1
